{
    "asset": {
        "format": "jpg",
        "id": "316e05af77730ca5b2f8d55d899185fa",
        "name": "Cat27_8.jpg",
        "path": "file:C:/Working/AWS%20Apps/Computer_vision/My_Project/Dataset/Raw_train/Cat27_8.jpg",
        "size": {
            "width": 1718,
            "height": 1124
        },
        "state": 2,
        "type": 1
    },
    "regions": [
        {
            "id": "_eY53cLpP",
            "type": "RECTANGLE",
            "tags": [
                "Door"
            ],
            "boundingBox": {
                "height": 110.0333419186449,
                "width": 118.03757380568975,
                "left": 1218.4920191700844,
                "top": 476.343811485785
            },
            "points": [
                {
                    "x": 1218.4920191700844,
                    "y": 476.343811485785
                },
                {
                    "x": 1336.529592975774,
                    "y": 476.343811485785
                },
                {
                    "x": 1336.529592975774,
                    "y": 586.3771534044299
                },
                {
                    "x": 1218.4920191700844,
                    "y": 586.3771534044299
                }
            ]
        },
        {
            "id": "WkpM-l3K5",
            "type": "RECTANGLE",
            "tags": [
                "Door"
            ],
            "boundingBox": {
                "height": 105.73039885247898,
                "width": 116.8080345067809,
                "left": 272.3470916338525,
                "top": 483.1056193601313
            },
            "points": [
                {
                    "x": 272.3470916338525,
                    "y": 483.1056193601313
                },
                {
                    "x": 389.1551261406334,
                    "y": 483.1056193601313
                },
                {
                    "x": 389.1551261406334,
                    "y": 588.8360182126103
                },
                {
                    "x": 272.3470916338525,
                    "y": 588.8360182126103
                }
            ]
        },
        {
            "id": "hv6rlMpWE",
            "type": "RECTANGLE",
            "tags": [
                "Door"
            ],
            "boundingBox": {
                "height": 105.11572485932373,
                "width": 114.34889962426195,
                "left": 900.6512980601893,
                "top": 765.8729337171221
            },
            "points": [
                {
                    "x": 900.6512980601893,
                    "y": 765.8729337171221
                },
                {
                    "x": 1015.0001976844513,
                    "y": 765.8729337171221
                },
                {
                    "x": 1015.0001976844513,
                    "y": 870.9886585764459
                },
                {
                    "x": 900.6512980601893,
                    "y": 870.9886585764459
                }
            ]
        },
        {
            "id": "1EuSZVm6l",
            "type": "RECTANGLE",
            "tags": [
                "Door"
            ],
            "boundingBox": {
                "height": 106.95980311730928,
                "width": 122.95584357072765,
                "left": 770.3181061266062,
                "top": 990.8574034492925
            },
            "points": [
                {
                    "x": 770.3181061266062,
                    "y": 990.8574034492925
                },
                {
                    "x": 893.2739496973337,
                    "y": 990.8574034492925
                },
                {
                    "x": 893.2739496973337,
                    "y": 1097.8172065666017
                },
                {
                    "x": 770.3181061266062,
                    "y": 1097.8172065666017
                }
            ]
        }
    ],
    "version": "2.2.0"
}