{
    "asset": {
        "format": "jpg",
        "id": "71aa09ba3885690f17d7c05f095730c8",
        "name": "Cat26_1.jpg",
        "path": "file:C:/Working/AWS%20Apps/Computer_vision/My_Project/Dataset/Raw_train/Cat26_1.jpg",
        "size": {
            "width": 1359,
            "height": 1464
        },
        "state": 2,
        "type": 1,
        "predicted": true
    },
    "regions": [
        {
            "id": "QqLa4u2Qp",
            "type": "RECTANGLE",
            "tags": [
                "Door"
            ],
            "boundingBox": {
                "height": 105.63764705882353,
                "width": 133.37062855057306,
                "left": 195.8640779601741,
                "top": 0
            },
            "points": [
                {
                    "x": 195.8640779601741,
                    "y": 0
                },
                {
                    "x": 329.2347065107471,
                    "y": 0
                },
                {
                    "x": 329.2347065107471,
                    "y": 105.63764705882353
                },
                {
                    "x": 195.8640779601741,
                    "y": 105.63764705882353
                }
            ]
        },
        {
            "id": "FrPhiXEAz",
            "type": "RECTANGLE",
            "tags": [
                "Door"
            ],
            "boundingBox": {
                "height": 130.3377613627995,
                "width": 107.52246210424727,
                "left": 518.5595328239015,
                "top": 205.4737076081353
            },
            "points": [
                {
                    "x": 518.5595328239015,
                    "y": 205.4737076081353
                },
                {
                    "x": 626.0819949281488,
                    "y": 205.4737076081353
                },
                {
                    "x": 626.0819949281488,
                    "y": 335.8114689709348
                },
                {
                    "x": 518.5595328239015,
                    "y": 335.8114689709348
                }
            ]
        },
        {
            "id": "_uF5pV18m",
            "type": "RECTANGLE",
            "tags": [
                "Door"
            ],
            "boundingBox": {
                "height": 132.63783991739493,
                "width": 110.9707287926546,
                "left": 516.2600404381146,
                "top": 909.2977453143412
            },
            "points": [
                {
                    "x": 516.2600404381146,
                    "y": 909.2977453143412
                },
                {
                    "x": 627.2307692307692,
                    "y": 909.2977453143412
                },
                {
                    "x": 627.2307692307692,
                    "y": 1041.935585231736
                },
                {
                    "x": 516.2600404381146,
                    "y": 1041.935585231736
                }
            ]
        },
        {
            "id": "o4YyHo_Lg",
            "type": "RECTANGLE",
            "tags": [
                "Door"
            ],
            "boundingBox": {
                "height": 115.2239902801323,
                "width": 132.60410769699797,
                "left": 258.7168932299929,
                "top": 720.6913038375147
            },
            "points": [
                {
                    "x": 258.7168932299929,
                    "y": 720.6913038375147
                },
                {
                    "x": 391.32100092699085,
                    "y": 720.6913038375147
                },
                {
                    "x": 391.32100092699085,
                    "y": 835.915294117647
                },
                {
                    "x": 258.7168932299929,
                    "y": 835.915294117647
                }
            ]
        }
    ],
    "version": "2.2.0"
}