{
    "asset": {
        "format": "png",
        "id": "89984a07351110d29152c1554d2f4dd7",
        "name": "Ic_RE0503_sommaire.png",
        "path": "file:C:/Working/AWS%20Apps/Computer_vision/My_Project/Dataset/Raw_train/Ic_RE0503_sommaire.png",
        "size": {
            "width": 1094,
            "height": 1115
        },
        "state": 2,
        "type": 1
    },
    "regions": [
        {
            "id": "ctAN8PccY",
            "type": "RECTANGLE",
            "tags": [
                "Door"
            ],
            "boundingBox": {
                "height": 104.67828798897659,
                "width": 111.16451612903225,
                "left": 758.2456653225806,
                "top": 588.0801867231538
            },
            "points": [
                {
                    "x": 758.2456653225806,
                    "y": 588.0801867231538
                },
                {
                    "x": 869.4101814516129,
                    "y": 588.0801867231538
                },
                {
                    "x": 869.4101814516129,
                    "y": 692.7584747121305
                },
                {
                    "x": 758.2456653225806,
                    "y": 692.7584747121305
                }
            ]
        },
        {
            "id": "6EXfU9Ql5",
            "type": "RECTANGLE",
            "tags": [
                "Door"
            ],
            "boundingBox": {
                "height": 96.84502424731033,
                "width": 89.78468402791617,
                "left": 551.8097521982414,
                "top": 364.8961522232779
            },
            "points": [
                {
                    "x": 551.8097521982414,
                    "y": 364.8961522232779
                },
                {
                    "x": 641.5944362261577,
                    "y": 364.8961522232779
                },
                {
                    "x": 641.5944362261577,
                    "y": 461.74117647058824
                },
                {
                    "x": 551.8097521982414,
                    "y": 461.74117647058824
                }
            ]
        },
        {
            "id": "2Ri6iZhG0",
            "type": "RECTANGLE",
            "tags": [
                "Door"
            ],
            "boundingBox": {
                "height": 89.26986878783977,
                "width": 99.30917338709673,
                "left": 543.8569556451613,
                "top": 160.83993513372886
            },
            "points": [
                {
                    "x": 543.8569556451613,
                    "y": 160.83993513372886
                },
                {
                    "x": 643.166129032258,
                    "y": 160.83993513372886
                },
                {
                    "x": 643.166129032258,
                    "y": 250.10980392156864
                },
                {
                    "x": 543.8569556451613,
                    "y": 250.10980392156864
                }
            ]
        },
        {
            "id": "N_RNpCiqN",
            "type": "RECTANGLE",
            "tags": [
                "Door"
            ],
            "boundingBox": {
                "height": 97.4718664681062,
                "width": 88.95053920526011,
                "left": 448.86720659809725,
                "top": 257.57911392405066
            },
            "points": [
                {
                    "x": 448.86720659809725,
                    "y": 257.57911392405066
                },
                {
                    "x": 537.8177458033573,
                    "y": 257.57911392405066
                },
                {
                    "x": 537.8177458033573,
                    "y": 355.0509803921569
                },
                {
                    "x": 448.86720659809725,
                    "y": 355.0509803921569
                }
            ]
        },
        {
            "id": "IlTJ_uG6F",
            "type": "RECTANGLE",
            "tags": [
                "Door"
            ],
            "boundingBox": {
                "height": 100.96160337552746,
                "width": 111.16451612903225,
                "left": 91.25856854838709,
                "top": 359.9050632911392
            },
            "points": [
                {
                    "x": 91.25856854838709,
                    "y": 359.9050632911392
                },
                {
                    "x": 202.42308467741933,
                    "y": 359.9050632911392
                },
                {
                    "x": 202.42308467741933,
                    "y": 460.8666666666667
                },
                {
                    "x": 91.25856854838709,
                    "y": 460.8666666666667
                }
            ]
        },
        {
            "id": "OjGBF7xBY",
            "type": "RECTANGLE",
            "tags": [
                "Door"
            ],
            "boundingBox": {
                "height": 89.32453462397615,
                "width": 94.96198831163146,
                "left": 528.556796660391,
                "top": 705.6048771407297
            },
            "points": [
                {
                    "x": 528.556796660391,
                    "y": 705.6048771407297
                },
                {
                    "x": 623.5187849720224,
                    "y": 705.6048771407297
                },
                {
                    "x": 623.5187849720224,
                    "y": 794.9294117647058
                },
                {
                    "x": 528.556796660391,
                    "y": 794.9294117647058
                }
            ]
        }
    ],
    "version": "2.2.0"
}