{
    "asset": {
        "format": "jpg",
        "id": "ef8236afda3603100efd95f87e55670b",
        "name": "Cat11_2.jpg",
        "path": "file:C:/Working/AWS%20Apps/Computer_vision/My_Project/Dataset/Raw_train/Cat11_2.jpg",
        "size": {
            "width": 839,
            "height": 1386
        },
        "state": 2,
        "type": 1,
        "predicted": true
    },
    "regions": [
        {
            "id": "y-kp0MOwg",
            "type": "RECTANGLE",
            "tags": [
                "Door"
            ],
            "boundingBox": {
                "height": 110.65913867710688,
                "width": 131.0466786355476,
                "left": 500.7922464093357,
                "top": 584.5304347826088
            },
            "points": [
                {
                    "x": 500.7922464093357,
                    "y": 584.5304347826088
                },
                {
                    "x": 631.8389250448834,
                    "y": 584.5304347826088
                },
                {
                    "x": 631.8389250448834,
                    "y": 695.1895734597157
                },
                {
                    "x": 500.7922464093357,
                    "y": 695.1895734597157
                }
            ]
        },
        {
            "id": "TLsj27dxE",
            "type": "RECTANGLE",
            "tags": [
                "Door"
            ],
            "boundingBox": {
                "height": 134.08043478260873,
                "width": 108.29335071707952,
                "left": 730.7066492829204,
                "top": 967.1869565217394
            },
            "points": [
                {
                    "x": 730.7066492829204,
                    "y": 967.1869565217394
                },
                {
                    "x": 838.9999999999999,
                    "y": 967.1869565217394
                },
                {
                    "x": 838.9999999999999,
                    "y": 1101.2673913043482
                },
                {
                    "x": 730.7066492829204,
                    "y": 1101.2673913043482
                }
            ]
        },
        {
            "id": "tASyO6_43",
            "type": "RECTANGLE",
            "tags": [
                "Door"
            ],
            "boundingBox": {
                "height": 129.56086956521742,
                "width": 109.13296393360316,
                "left": 355.50847457627117,
                "top": 864.7434782608697
            },
            "points": [
                {
                    "x": 355.50847457627117,
                    "y": 864.7434782608697
                },
                {
                    "x": 464.6414385098743,
                    "y": 864.7434782608697
                },
                {
                    "x": 464.6414385098743,
                    "y": 994.3043478260871
                },
                {
                    "x": 355.50847457627117,
                    "y": 994.3043478260871
                }
            ]
        }
    ],
    "version": "2.2.0"
}